setup.py
citrees/__init__.py
citrees/feature_selectors.py
citrees/scorers.py
citrees/utils.py
citrees.egg-info/PKG-INFO
citrees.egg-info/SOURCES.txt
citrees.egg-info/dependency_links.txt
citrees.egg-info/top_level.txt